{"activityList":[{"summaryId":"3647218751","durationInSeconds":467,"startTimeInSeconds":1557827333,"startTimeOffsetInSeconds":-14400,"activityType":"RUNNING","averageHeartRateInBeatsPerMinute":162,"averageRunCadenceInStepsPerMinute":148.79688,"averageSpeedInMetersPerSecond":3.319,"averagePaceInMinutesPerKilometer":5.021593,"activeKilocalories":97,"deviceName":"fenix 5X Plus","distanceInMeters":1551.01,"maxHeartRateInBeatsPerMinute":174,"maxPaceInMinutesPerKilometer":4.7254515,"maxRunCadenceInStepsPerMinute":172,"maxSpeedInMetersPerSecond":3.527,"startingLatitudeInDegree":40.765843223780394,"startingLongitudeInDegree":-73.97647311910987,"steps":1156,"totalElevationGainInMeters":0.03,"totalElevationLossInMeters":0.03},{"summaryId":"3647203827","durationInSeconds":2077,"startTimeInSeconds":1557825230,"startTimeOffsetInSeconds":-14400,"activityType":"RUNNING","averageHeartRateInBeatsPerMinute":164,"averageRunCadenceInStepsPerMinute":167.23438,"averageSpeedInMetersPerSecond":3.472,"averagePaceInMinutesPerKilometer":4.8003073,"activeKilocalories":429,"deviceName":"fenix 5X Plus","distanceInMeters":7214.23,"maxHeartRateInBeatsPerMinute":184,"maxPaceInMinutesPerKilometer":3.8831937,"maxRunCadenceInStepsPerMinute":172,"maxSpeedInMetersPerSecond":4.292,"startingLatitudeInDegree":40.76548330485821,"startingLongitudeInDegree":-73.9762311335653,"steps":5816,"totalElevationGainInMeters":0.43,"totalElevationLossInMeters":0.44},{"summaryId":"3647140396","durationInSeconds":483,"startTimeInSeconds":1557824697,"startTimeOffsetInSeconds":-14400,"activityType":"RUNNING","averageHeartRateInBeatsPerMinute":142,"averageRunCadenceInStepsPerMinute":162.10938,"averageSpeedInMetersPerSecond":2.659,"averagePaceInMinutesPerKilometer":6.2680206,"activeKilocalories":79,"deviceName":"fenix 5X Plus","distanceInMeters":1285.14,"maxHeartRateInBeatsPerMinute":157,"maxPaceInMinutesPerKilometer":4.335761,"maxRunCadenceInStepsPerMinute":172,"maxSpeedInMetersPerSecond":3.844,"startingLatitudeInDegree":40.75384461320937,"startingLongitudeInDegree":-73.98426426574588,"steps":1310,"totalElevationGainInMeters":0.05,"totalElevationLossInMeters":0.09},{"summaryId":"3676976277","durationInSeconds":2066,"startTimeInSeconds":1558633594,"startTimeOffsetInSeconds":3600,"activityType":"CYCLING","averageBikeCadenceInRoundsPerMinute":68,"averageSpeedInMetersPerSecond":4.695,"averagePaceInMinutesPerKilometer":3.5498757,"activeKilocalories":203,"deviceName":"Edge 820","distanceInMeters":9699.54,"maxBikeCadenceInRoundsPerMinute":88,"maxPaceInMinutesPerKilometer":2.0627062,"maxSpeedInMetersPerSecond":8.08,"startingLatitudeInDegree":51.514259576797485,"startingLongitudeInDegree":-0.1066887192428112,"totalElevationGainInMeters":0.19,"totalElevationLossInMeters":0.26},{"summaryId":"3675343924","durationInSeconds":2309,"startTimeInSeconds":1558597005,"startTimeOffsetInSeconds":3600,"activityType":"CYCLING","averageBikeCadenceInRoundsPerMinute":64,"averageHeartRateInBeatsPerMinute":123,"averageSpeedInMetersPerSecond":4.403,"averagePaceInMinutesPerKilometer":3.7852979,"activeKilocalories":212,"deviceName":"Edge 820","distanceInMeters":10168.5,"maxBikeCadenceInRoundsPerMinute":99,"maxHeartRateInBeatsPerMinute":151,"maxPaceInMinutesPerKilometer":1.7988845,"maxSpeedInMetersPerSecond":9.265,"startingLatitudeInDegree":51.47547718137503,"startingLongitudeInDegree":-0.19799253903329372,"totalElevationGainInMeters":0.24,"totalElevationLossInMeters":0.17},{"summaryId":"3674145278","durationInSeconds":3023,"startTimeInSeconds":1558551989,"startTimeOffsetInSeconds":3600,"activityType":"INDOOR_CARDIO","averageHeartRateInBeatsPerMinute":123,"averageSpeedInMetersPerSecond":0,"activeKilocalories":346,"deviceName":"fenix 5X Plus","distanceInMeters":0,"maxHeartRateInBeatsPerMinute":166,"totalElevationGainInMeters":0,"totalElevationLossInMeters":0},{"summaryId":"3673767094","durationInSeconds":2289,"startTimeInSeconds":1558546742,"startTimeOffsetInSeconds":3600,"activityType":"CYCLING","averageBikeCadenceInRoundsPerMinute":67,"averageSpeedInMetersPerSecond":4.491,"averagePaceInMinutesPerKilometer":3.7111256,"activeKilocalories":202,"deviceName":"Edge 820","distanceInMeters":10281.27,"maxBikeCadenceInRoundsPerMinute":83,"maxPaceInMinutesPerKilometer":2.2025461,"maxSpeedInMetersPerSecond":7.567,"startingLatitudeInDegree":51.516502071172,"startingLongitudeInDegree":-0.10215285234153271,"totalElevationGainInMeters":0.19,"totalElevationLossInMeters":0.32},{"summaryId":"3642809165","durationInSeconds":6686,"startTimeInSeconds":1557676859,"startTimeOffsetInSeconds":3600,"activityType":"INDOOR_CARDIO","averageHeartRateInBeatsPerMinute":126,"averageSpeedInMetersPerSecond":0,"activeKilocalories":685,"deviceName":"fenix 5X Plus","distanceInMeters":0,"maxHeartRateInBeatsPerMinute":181,"totalElevationGainInMeters":0,"totalElevationLossInMeters":0},{"summaryId":"3641253953","durationInSeconds":3132,"startTimeInSeconds":1557654542,"startTimeOffsetInSeconds":3600,"activityType":"RUNNING","averageHeartRateInBeatsPerMinute":170,"averageRunCadenceInStepsPerMinute":162,"averageSpeedInMetersPerSecond":3.081,"averagePaceInMinutesPerKilometer":5.409499,"activeKilocalories":658,"deviceName":"fenix 5X Plus","distanceInMeters":9650.07,"maxHeartRateInBeatsPerMinute":183,"maxPaceInMinutesPerKilometer":4.0591006,"maxRunCadenceInStepsPerMinute":201,"maxSpeedInMetersPerSecond":4.106,"startingLatitudeInDegree":51.47034527733922,"startingLongitudeInDegree":-0.19593042321503162,"steps":8472,"totalElevationGainInMeters":0.2,"totalElevationLossInMeters":0.27},{"summaryId":"3679802647","durationInSeconds":2068,"startTimeInSeconds":1558716875,"startTimeOffsetInSeconds":3600,"activityType":"CYCLING","averageBikeCadenceInRoundsPerMinute":67,"averageSpeedInMetersPerSecond":4.817,"averagePaceInMinutesPerKilometer":3.4599683,"activeKilocalories":196,"deviceName":"Edge 820","distanceInMeters":9964.65,"maxBikeCadenceInRoundsPerMinute":95,"maxPaceInMinutesPerKilometer":1.7721071,"maxSpeedInMetersPerSecond":9.405,"startingLatitudeInDegree":51.51619881391525,"startingLongitudeInDegree":-0.10183031670749187,"totalElevationGainInMeters":0.17,"totalElevationLossInMeters":0.26},{"summaryId":"3678347096","durationInSeconds":2073,"startTimeInSeconds":1558679224,"startTimeOffsetInSeconds":3600,"activityType":"CYCLING","averageBikeCadenceInRoundsPerMinute":68,"averageSpeedInMetersPerSecond":5.016,"averagePaceInMinutesPerKilometer":3.322701,"activeKilocalories":233,"deviceName":"Edge 820","distanceInMeters":10402.55,"maxBikeCadenceInRoundsPerMinute":95,"maxPaceInMinutesPerKilometer":1.874344,"maxSpeedInMetersPerSecond":8.892,"startingLatitudeInDegree":51.47192099131644,"startingLongitudeInDegree":-0.19599705934524536,"totalElevationGainInMeters":0.29,"totalElevationLossInMeters":0.15},{"summaryId":"3668777546","durationInSeconds":2216,"startTimeInSeconds":1558419718,"startTimeOffsetInSeconds":3600,"activityType":"CYCLING","averageBikeCadenceInRoundsPerMinute":66,"averageSpeedInMetersPerSecond":4.685,"averagePaceInMinutesPerKilometer":3.557453,"activeKilocalories":233,"deviceName":"Edge 820","distanceInMeters":10384.71,"maxBikeCadenceInRoundsPerMinute":100,"maxPaceInMinutesPerKilometer":1.7175047,"maxSpeedInMetersPerSecond":9.704,"startingLatitudeInDegree":51.47212240844965,"startingLongitudeInDegree":-0.19605363719165325,"totalElevationGainInMeters":0.28,"totalElevationLossInMeters":0.21},{"summaryId":"3627553841","durationInSeconds":1909,"startTimeInSeconds":1557253615,"startTimeOffsetInSeconds":3600,"activityType":"CYCLING","averageBikeCadenceInRoundsPerMinute":71,"averageSpeedInMetersPerSecond":5.225,"averagePaceInMinutesPerKilometer":3.1897929,"activeKilocalories":217,"deviceName":"Edge 820","distanceInMeters":9974.3,"maxBikeCadenceInRoundsPerMinute":95,"maxPaceInMinutesPerKilometer":2.0745165,"maxSpeedInMetersPerSecond":8.034,"startingLatitudeInDegree":51.51620560325682,"startingLongitudeInDegree":-0.10201656259596348,"totalElevationGainInMeters":0.19,"totalElevationLossInMeters":0.3},{"summaryId":"3625596416","durationInSeconds":2105,"startTimeInSeconds":1557209607,"startTimeOffsetInSeconds":3600,"activityType":"CYCLING","averageBikeCadenceInRoundsPerMinute":67,"averageSpeedInMetersPerSecond":4.84,"averagePaceInMinutesPerKilometer":3.443526,"activeKilocalories":218,"deviceName":"Edge 820","distanceInMeters":10189.21,"maxBikeCadenceInRoundsPerMinute":99,"maxPaceInMinutesPerKilometer":1.7738045,"maxSpeedInMetersPerSecond":9.396,"startingLatitudeInDegree":51.47225392051041,"startingLongitudeInDegree":-0.19623384810984135,"totalElevationGainInMeters":0.29,"totalElevationLossInMeters":0.15},{"summaryId":"3621423464","durationInSeconds":6207,"startTimeInSeconds":1557072316,"startTimeOffsetInSeconds":3600,"activityType":"INDOOR_CARDIO","averageHeartRateInBeatsPerMinute":129,"averageSpeedInMetersPerSecond":0,"activeKilocalories":748,"deviceName":"fenix 5X Plus","distanceInMeters":0,"maxHeartRateInBeatsPerMinute":184,"totalElevationGainInMeters":0,"totalElevationLossInMeters":0},{"summaryId":"3619680395","durationInSeconds":5079,"startTimeInSeconds":1557045459,"startTimeOffsetInSeconds":3600,"activityType":"RUNNING","averageHeartRateInBeatsPerMinute":159,"averageRunCadenceInStepsPerMinute":156.20312,"averageSpeedInMetersPerSecond":3.001,"averagePaceInMinutesPerKilometer":5.5537047,"activeKilocalories":918,"deviceName":"fenix 5X Plus","distanceInMeters":15245.14,"maxHeartRateInBeatsPerMinute":185,"maxPaceInMinutesPerKilometer":4.154204,"maxRunCadenceInStepsPerMinute":172,"maxSpeedInMetersPerSecond":4.012,"startingLatitudeInDegree":51.4518637675792,"startingLongitudeInDegree":-0.2555656526237726,"steps":13176,"totalElevationGainInMeters":1.63,"totalElevationLossInMeters":1.54},{"summaryId":"3682898746","durationInSeconds":2540,"startTimeInSeconds":1558797720,"startTimeOffsetInSeconds":3600,"activityType":"RUNNING","averageHeartRateInBeatsPerMinute":155,"averageRunCadenceInStepsPerMinute":160.09375,"averageSpeedInMetersPerSecond":2.989,"averagePaceInMinutesPerKilometer":5.5760007,"activeKilocalories":471,"deviceName":"fenix 5X Plus","distanceInMeters":7594.69,"maxHeartRateInBeatsPerMinute":180,"maxPaceInMinutesPerKilometer":4.222616,"maxRunCadenceInStepsPerMinute":174,"maxSpeedInMetersPerSecond":3.947,"startingLatitudeInDegree":51.47157615981996,"startingLongitudeInDegree":-0.19594316370785236,"steps":6758,"totalElevationGainInMeters":0.25,"totalElevationLossInMeters":0.22},{"summaryId":"3637221178","durationInSeconds":2461,"startTimeInSeconds":1557554989,"startTimeOffsetInSeconds":3600,"activityType":"RUNNING","averageHeartRateInBeatsPerMinute":158,"averageRunCadenceInStepsPerMinute":145.92188,"averageSpeedInMetersPerSecond":2.799,"averagePaceInMinutesPerKilometer":5.954508,"activeKilocalories":467,"deviceName":"fenix 5X Plus","distanceInMeters":6890.91,"maxHeartRateInBeatsPerMinute":185,"maxPaceInMinutesPerKilometer":4.0591006,"maxRunCadenceInStepsPerMinute":250,"maxSpeedInMetersPerSecond":4.106,"startingLatitudeInDegree":51.558002550154924,"startingLongitudeInDegree":-0.688978610560298,"steps":6112,"totalElevationGainInMeters":0.95,"totalElevationLossInMeters":0.95},{"summaryId":"3614937403","durationInSeconds":1859,"startTimeInSeconds":1556907042,"startTimeOffsetInSeconds":3600,"activityType":"CYCLING","averageBikeCadenceInRoundsPerMinute":72,"averageHeartRateInBeatsPerMinute":122,"averageSpeedInMetersPerSecond":5.439,"averagePaceInMinutesPerKilometer":3.0642889,"activeKilocalories":191,"deviceName":"Edge 820","distanceInMeters":10113.81,"maxBikeCadenceInRoundsPerMinute":89,"maxHeartRateInBeatsPerMinute":142,"maxPaceInMinutesPerKilometer":1.8133681,"maxSpeedInMetersPerSecond":9.191,"startingLatitudeInDegree":51.516444655135274,"startingLongitudeInDegree":-0.1017498504370451,"totalElevationGainInMeters":0.17,"totalElevationLossInMeters":0.31},{"summaryId":"3688325278","durationInSeconds":1102,"startTimeInSeconds":1558953361,"startTimeOffsetInSeconds":3600,"activityType":"RUNNING","averageHeartRateInBeatsPerMinute":144,"averageRunCadenceInStepsPerMinute":159.65625,"averageSpeedInMetersPerSecond":2.799,"averagePaceInMinutesPerKilometer":5.954508,"activeKilocalories":191,"deviceName":"fenix 5X Plus","distanceInMeters":3085.64,"maxHeartRateInBeatsPerMinute":165,"maxPaceInMinutesPerKilometer":4.7254515,"maxRunCadenceInStepsPerMinute":166,"maxSpeedInMetersPerSecond":3.527,"startingLatitudeInDegree":51.47119126282632,"startingLongitudeInDegree":-0.19672435708343983,"steps":2928,"totalElevationGainInMeters":0.08,"totalElevationLossInMeters":0.03}],"paging":{"total":20,"start":0,"limit":20}}