{"session":{"session_id":9457,"owner":{"id":1544,"first_name":"Brice","last_name":"Rosenzweig","email":"brice_rosenzweig@yahoo.com","pro":false,"score":36.621865480264,"total_strokes":56319,"level":2,"profile_picture":"http://api.babolatplay.as44099.com/bundles/babolatfront/images/avatar.png","privacy":"FULL","hand":"0","speed_unit":"kmh"},"start_at":"2014-02-12 20:01:11","end_at":"2014-02-12 20:57:16","qualified":true,"qualified_at":"2014-02-12 21:00:49","records":[{"id":26715,"record_id":17,"record_label":"maxPowerServesLabel","score":56,"date":"2014-02-12 21:00:49"},{"id":26716,"record_id":22,"record_label":"recordTrainingTotalPlayTimeLabel","score":54,"date":"2014-02-12 21:00:49"}],"medias":[],"title":null,"comment":null,"type":"training","team":null,"venue":"indoor","tennis_surface":"hard","feeling":"nice","score":null,"log_file":"/home/www-babolat/www/en.babolatplay.com/app/data/sessions/f/f3/f33/f337/user_1544/2014-02-12_21-00-49_95437413ba288fece626102b2dae3396.bin","firmware_version":"00.08.09","total_play_time":54,"effective_play_time":14,"total_strokes":292,"total_forehands":160,"total_forehands_flat":49,"total_forehands_sliced":6,"total_forehands_lifted":105,"total_backhands":120,"total_backhands_flat":92,"total_backhands_sliced":19,"total_backhands_lifted":9,"total_serves":6,"total_first_serves":5,"total_first_serves_flat":5,"total_first_serves_effect":0,"total_second_serves":1,"total_second_serves_flat":1,"total_second_serves_effect":0,"total_smash":6,"total_volley":null,"total_forehands_volley":null,"total_forehands_volley_flat":null,"total_forehands_volley_sliced":null,"total_forehands_volley_lifted":null,"total_forehands_volley_effect":null,"total_backhands_volley":null,"total_backhands_volley_flat":null,"total_backhands_volley_sliced":null,"total_backhands_volley_lifted":null,"total_backhands_volley_effect":null,"average_power":46.493150684932,"average_power_forehands":46.54375,"average_power_forehands_flat":45.510204081633,"average_power_forehands_sliced":43,"average_power_forehands_lifted":47.228571428571,"average_power_backhands":46.275,"average_power_backhands_flat":47.54347826087,"average_power_backhands_sliced":43.105263157895,"average_power_backhands_lifted":40,"average_power_serves":49.166666666667,"average_power_serves_flat":49.166666666667,"average_power_serves_effect":0,"average_power_first_serves":49.4,"average_power_first_serves_flat":49.4,"average_power_first_serves_effect":0,"average_power_second_serves":48,"average_power_second_serves_flat":48,"average_power_second_serves_effect":0,"average_power_smash":46.833333333333,"average_power_volley":null,"average_power_volley_effect":null,"average_power_volley_flat":null,"average_power_forehands_volley":null,"average_power_forehands_volley_flat":null,"average_power_forehands_volley_sliced":null,"average_power_forehands_volley_lifted":null,"average_power_forehands_volley_effect":null,"average_power_backhands_volley":null,"average_power_backhands_volley_flat":null,"average_power_backhands_volley_sliced":null,"average_power_backhands_volley_lifted":null,"average_power_backhands_volley_effect":null,"average_effect_level_forehands":43.95,"average_effect_level_backhands":26.658333333333,"average_effect_level_serves":25.3,"average_effect_level_first_serves":27.6,"average_effect_level_second_serves":23,"average_effect_level_forehands_sliced":66.333333333333,"average_effect_level_forehands_lifted":50.666666666667,"average_effect_level_backhands_sliced":51.736842105263,"average_effect_level_backhands_lifted":61.444444444444,"max_effect_level_forehands":null,"max_effect_level_backhands":null,"max_effect_level_serves":null,"max_effect_level_first_serves":null,"max_effect_level_second_serves":null,"max_effect_level_forehands_sliced":null,"max_effect_level_forehands_lifted":null,"max_effect_level_backhands_sliced":null,"max_effect_level_backhands_lifted":null,"max_power_forehands":57,"max_power_forehands_flat":56,"max_power_forehands_sliced":50,"max_power_forehands_lifted":50,"max_power_backhands":55,"max_power_backhands_flat":55,"max_power_backhands_sliced":51,"max_power_serves":56,"max_power_serves_flat":56,"max_power_serves_effect":0,"max_power_first_serves":56,"max_power_first_serves_flat":56,"max_power_first_serves_effect":0,"max_power_second_serves":48,"max_power_second_serves_flat":48,"max_power_second_serves_effect":0,"max_power_smash":51,"max_power_volley":null,"max_power_volley_effect":null,"max_power_volley_flat":null,"max_power_forehands_volley":null,"max_power_forehands_volley_flat":null,"max_power_forehands_volley_sliced":null,"max_power_forehands_volley_lifted":null,"max_power_forehands_volley_effect":null,"max_power_backhands_volley":null,"max_power_backhands_volley_flat":null,"max_power_backhands_volley_sliced":null,"max_power_backhands_volley_lifted":null,"max_power_backhands_volley_effect":null,"max_speed_serves":null,"max_speed_serves_flat":null,"max_speed_serves_effect":null,"max_speed_first_serves":null,"max_speed_first_serves_flat":null,"max_speed_first_serves_effect":null,"max_speed_second_serves":null,"max_speed_second_serves_flat":null,"max_speed_second_serves_effect":null,"average_speed_serves":null,"average_speed_serves_flat":null,"average_speed_serves_effect":null,"average_speed_first_serves":null,"average_speed_first_serves_flat":null,"average_speed_first_serves_effect":null,"average_speed_second_serves":null,"average_speed_second_serves_flat":null,"average_speed_second_serves_effect":null,"heatmap":{"up":18.835616438356,"down":11.986301369863,"left":20.205479452055,"right":15.41095890411,"center":33.561643835616},"heatmap_forehands":{"up":20,"down":11.25,"left":21.875,"right":13.125,"center":33.75},"heatmap_backhands":{"up":16.666666666667,"down":12.5,"left":18.333333333333,"right":16.666666666667,"center":35.833333333333},"heatmap_serves":{"up":0,"down":16.666666666667,"left":0,"right":66.666666666667,"center":16.666666666667},"heatmap_smash":{"up":50,"down":16.666666666667,"left":33.333333333333,"right":0,"center":0},"heatmap_volley":null,"energy":597,"strokes_per_minute":20.9,"max_rally":11,"technical":28,"regularity":23,"favorite":false,"cuePoints":[{"time":0,"totalStrokes":125,"averagePower":46.096,"energy":255,"regularity":25},{"time":801,"totalStrokes":99,"averagePower":47.232323232323,"energy":204,"regularity":20},{"time":2298,"totalStrokes":68,"averagePower":46.147058823529,"energy":139,"regularity":25}],"with_players":[],"declarative":false,"racket":[]}}